SAFIRshell/__init__.py
SAFIRshell/runSAFIR.py
SAFIRshell/shell/__init__.py
SAFIRshell/shell/__main__.py
SAFIRshell-0.0.3.dist-info/LICENSE
SAFIRshell-0.0.3.dist-info/METADATA
SAFIRshell-0.0.3.dist-info/WHEEL
SAFIRshell-0.0.3.dist-info/top_level.txt
SAFIRshell-0.0.3.dist-info/RECORD
