Metadata-Version: 2.1
Name: SAFIRshell
Version: 0.0.3
Summary: SAFIR shell
Home-page: https://github.com/rvcoile/SAFIRshell
Author: Ruben Van Coile
Author-email: ruben.vancoile@gmail.com
License: UNKNOWN
Platform: UNKNOWN
Classifier: Programming Language :: Python :: 3
Classifier: License :: OSI Approved :: MIT License
Classifier: Operating System :: OS Independent
